tinymon/__init__.py
tinymon/imagectrl.py
tinymon/mysignal.py
tinymon/preview_cv.py
tinymon/preview_udp.py
tinymon/previewmanager.py
tinymon/textctrl.py
tinymon/tinymon.py
tinymon/font/NanumBarunGothicLight.ttf
tinymon/image/novideo.png
tinymon/image/videonot.png
tinymon-0.1.11.dist-info/LICENSE
tinymon-0.1.11.dist-info/METADATA
tinymon-0.1.11.dist-info/WHEEL
tinymon-0.1.11.dist-info/top_level.txt
tinymon-0.1.11.dist-info/RECORD
