Metadata-Version: 2.1
Name: tinymon
Version: 0.1.11
Summary: tinymon
Home-page: https://gitlab.com/telelian/peripheral-library/tinymon
Author: mrzjo
Author-email: mrzjo05@gmail.com
License: UNKNOWN
Platform: UNKNOWN
Classifier: Development Status :: 4 - Beta
Classifier: Programming Language :: Python
Classifier: Programming Language :: Python :: 3
Classifier: Topic :: System :: Hardware
Requires-Dist: numpy (>=1.18.1)
Requires-Dist: Pillow (>=7.0.0)
Requires-Dist: ssd1362-py (>=0.1.1)
Requires-Dist: loguru (>=0.4.1)
